npy2bdv/__init__.py
npy2bdv/examples.py
npy2bdv/npy2bdv.py
npy2bdv/test.py
test/__init__.py
test/sample.py
test/test_h5.py
test/test_n5.py
npy2bdv-1.0.8.dist-info/LICENSE
npy2bdv-1.0.8.dist-info/METADATA
npy2bdv-1.0.8.dist-info/WHEEL
npy2bdv-1.0.8.dist-info/top_level.txt
npy2bdv-1.0.8.dist-info/RECORD
