Metadata-Version: 2.1
Name: npy2bdv
Version: 1.0.8
Summary: Package for writing/reading 3d numpy arrays to/from HDF5 files (for Fiji/BigDataViewer/BigStitcher).
Home-page: https://github.com/nvladimus/npy2bdv
Author: Nikita Vladimirov
Author-email: nvladimus@gmail.com
License: UNKNOWN
Platform: UNKNOWN
Requires-Dist: h5py
Requires-Dist: numpy
Requires-Dist: scikit-image
Requires-Dist: tqdm
